[
    {
        "code":192895,
        "name":"Tierney",
        "expected_score":15,
        "rank":"player",
        "club":3,
        "position":2,
        "buy_price":5.1
    },
    {
        "code":226597,
        "name":"Gabriel",
        "expected_score":21,
        "rank":"player",
        "club":3,
        "position":2,
        "buy_price":5.3
    },
    {
        "code":225321,
        "name":"Ramsdale",
        "expected_score":18,
        "rank":"player",
        "club":3,
        "position":1,
        "buy_price":5.1
    },
    {
        "code":110735,
        "name":"Webster",
        "expected_score":7,
        "rank":"sub",
        "club":36,
        "position":2,
        "buy_price":4.4
    },
    {
        "code":50175,
        "name":"Welbeck",
        "expected_score":3,
        "rank":"sub",
        "club":36,
        "position":4,
        "buy_price":5.9
    },
    {
        "code":221399,
        "name":"Harrison",
        "expected_score":11,
        "rank":"player",
        "club":2,
        "position":3,
        "buy_price":5.5
    },
    {
        "code":97032,
        "name":"van Dijk",
        "expected_score":17,
        "rank":"player",
        "club":14,
        "position":2,
        "buy_price":6.7
    },
    {
        "code":116643,
        "name":"Fabinho",
        "expected_score":18,
        "rank":"player",
        "club":14,
        "position":3,
        "buy_price":5.4
    },
    {
        "code":122798,
        "name":"Robertson",
        "expected_score":20,
        "rank":"player",
        "club":14,
        "position":2,
        "buy_price":7.1
    },
    {
        "code":61366,
        "name":"De Bruyne",
        "expected_score":8,
        "rank":"player",
        "club":43,
        "position":3,
        "buy_price":12.1
    },
    {
        "code":170137,
        "name":"Saint-Maximin",
        "expected_score":3,
        "rank":"sub",
        "club":4,
        "position":4,
        "buy_price":6.9
    },
    {
        "code":78830,
        "name":"Kane",
        "expected_score":8,
        "rank":"player",
        "club":6,
        "position":4,
        "buy_price":12.2
    },
    {
        "code":178186,
        "name":"Bowen",
        "expected_score":9,
        "rank":"player",
        "club":21,
        "position":3,
        "buy_price":7.0
    },
    {
        "code":151589,
        "name":"Dendoncker",
        "expected_score":9,
        "rank":"player",
        "club":39,
        "position":3,
        "buy_price":4.7
    },
    {
        "code":149065,
        "name":"S\u00e1",
        "expected_score":9,
        "rank":"sub",
        "club":39,
        "position":1,
        "buy_price":5.2
    }
]